maxima_interface/__init__.py
maxima_interface/maxima_interface.py
maxima_interface-0.1.1.dist-info/LICENSE
maxima_interface-0.1.1.dist-info/METADATA
maxima_interface-0.1.1.dist-info/WHEEL
maxima_interface-0.1.1.dist-info/top_level.txt
maxima_interface-0.1.1.dist-info/RECORD
