Metadata-Version: 2.1
Name: maxima-interface
Version: 0.1.1
Summary: Interfacing Maxima CAS with Python
Author-email: "Konstantin (k0nze) Lübeck" <admin@konze.org>
License: BSD 3-Clause License
Project-URL: Homepage, https://github.com/k0nze/maxima_interface
Keywords: maxima,cas
Classifier: License :: OSI Approved :: BSD License
Classifier: Operating System :: Unix
Classifier: Programming Language :: Python
Classifier: Programming Language :: Python :: 3
Requires-Python: >=3.9
License-File: LICENSE
Requires-Dist: psutil (==5.9.*)
Provides-Extra: dev
Requires-Dist: pre-commit ; extra == 'dev'
Requires-Dist: bumpver ; extra == 'dev'
